{
  "fuente": "GENERAL_ES",
  "source_name": "General en español",
  "feed_url": "https://www.abc.es/rss/atom/economia/",
  "title": "Francisco Iñareta, experto en vivienda, explica qué va a pasar con los precios en 2026: «La emergencia del alquiler es total»",
  "link": "https://www.abc.es/economia/francisco-inareta-experto-vivienda-explica-pasara-precios-20251231081500-nt.html",
  "link_hash": "98033691",
  "published": "2025-12-31T10:26:24+00:00",
  "retrieved": "2026-01-01T17:31:28.424274+00:00"
}